pytabcmd/__init__.py
pytabcmd/pytabcmd.py
pytabcmd/settings.py
pytabcmd-9.2.0.dist-info/DESCRIPTION.rst
pytabcmd-9.2.0.dist-info/METADATA
pytabcmd-9.2.0.dist-info/RECORD
pytabcmd-9.2.0.dist-info/WHEEL
pytabcmd-9.2.0.dist-info/metadata.json
pytabcmd-9.2.0.dist-info/top_level.txt
