Metadata-Version: 2.0
Name: pytabcmd
Version: 9.2.0
Summary: A tabcmd wrapper for Python
Home-page: https://github.com/AccesoGroup/pytabcmd
Author: MiguelSR
Author-email: miguelsr87@gmail.com
License: MIT
Keywords: tabcmb tableau
Platform: UNKNOWN
Requires-Dist: configparser
